micro_lisp_tool/__init__.py
micro_lisp_tool/__main__.py
micro_lisp_tool/lisp_file.py
micro_lisp_tool/protocol.py
micro_lisp_tool/put_file.py
micro_lisp_tool/run_file.py
micro_lisp_tool_amotzek-1.0.7.dist-info/LICENSE
micro_lisp_tool_amotzek-1.0.7.dist-info/METADATA
micro_lisp_tool_amotzek-1.0.7.dist-info/WHEEL
micro_lisp_tool_amotzek-1.0.7.dist-info/top_level.txt
micro_lisp_tool_amotzek-1.0.7.dist-info/RECORD
