Metadata-Version: 2.1
Name: micro-lisp-tool-amotzek
Version: 1.0.7
Summary: Run and upload Lisp programs and use the read-eval-print loop with ESP32 boards flashed with Micro Lisp
Home-page: https://bitbucket.org/amotzek/micro-lisp-tool/src/master/
Author: Andreas Motzek
Author-email: andreas-motzek@t-online.de
License: UNKNOWN
Platform: UNKNOWN
Classifier: Programming Language :: Python :: 3
Classifier: Operating System :: OS Independent
Classifier: Development Status :: 4 - Beta
Classifier: Environment :: Console
Classifier: Intended Audience :: Developers
Classifier: Topic :: Software Development :: Embedded Systems
Classifier: Topic :: Terminals :: Serial
Requires-Python: >=3.6
Requires-Dist: pyserial (>=3.0)
